{
  "version": "5",
  "dialect": "pg",
  "entries": [
    {
      "idx": 0,
      "version": "5",
      "when": 1702027052223,
      "tag": "0000_bitter_thing",
      "breakpoints": true
    },
    {
      "idx": 1,
      "version": "5",
      "when": 1702069553603,
      "tag": "0001_bumpy_bastion",
      "breakpoints": true
    },
    {
      "idx": 2,
      "version": "5",
      "when": 1702159977304,
      "tag": "0002_silly_speed_demon",
      "breakpoints": true
    },
    {
      "idx": 3,
      "version": "5",
      "when": 1707130129082,
      "tag": "0003_curly_magma",
      "breakpoints": true
    }
  ]
}